norris/__init__.py
norris-0.1.dist-info/METADATA
norris-0.1.dist-info/RECORD
norris-0.1.dist-info/WHEEL
norris-0.1.dist-info/top_level.txt
