Metadata-Version: 2.1
Name: norris
Version: 0.1
Summary: Wrapper for the ICNDB API
Home-page: http://github.com/chriscardillo/norris_py
Author: Chris Cardillo
Author-email: CFCardillo23@gmail.com
License: MIT
Platform: UNKNOWN
Requires-Dist: requests
Requires-Dist: pandas
